{
  "streams": [
    {
      "title": "I'm excited!",
      "description": "This REALLY works!!",
      "id": 1
    },
    {
      "title": "DOES IT WORK NOW?",
      "description": "Vitae facilis dolore",
      "userId": "107817050335266894763",
      "id": 2
    },
    {
      "title": "Qui explicabo Quae ",
      "description": "Harum veniam molest",
      "userId": "107817050335266894763",
      "id": 3
    },
    {
      "title": "Aliquid eaque sapien",
      "description": "Quisquam autem volup",
      "userId": "107817050335266894763",
      "id": 4
    },
    {
      "title": "Nostrum quam officia",
      "description": "Voluptatibus nemo ip",
      "id": 5
    },
    {
      "title": "Nulla molestias aut ",
      "description": "Sit vitae accusanti",
      "id": 6
    },
    {
      "title": "ANOTHER TEST",
      "description": "And another",
      "id": 7
    },
    {
      "title": "NUKK NUKK ",
      "description": "Quaerat placeat imp",
      "userId": "107817050335266894763",
      "id": 8
    }
  ]
}